{
  "id": "ciencia_basica",
  "questions": [
    {
      "questionText": "¿Cuál es el elemento químico más abundante en el universo?",
      "options": ["Oxígeno", "Carbono", "Hidrógeno", "Helio"],
      "correctAnswerIndex": 2,
      "explanation": "El hidrógeno representa aproximadamente el 75% de toda la materia normal del universo."
    },
    {
      "questionText": "¿Qué planeta es conocido como el Planeta Rojo?",
      "options": ["Júpiter", "Marte", "Venus", "Saturno"],
      "correctAnswerIndex": 1,
      "explanation": "Marte es conocido como el Planeta Rojo debido a la gran cantidad de óxido de hierro en su superficie."
    },
    {
      "questionText": "¿Cuántos huesos tiene el cuerpo humano adulto?",
      "options": ["198", "206", "215", "189"],
      "correctAnswerIndex": 1,
      "explanation": "Un adulto tiene 206 huesos, mientras que los bebés nacen con aproximadamente 270."
    }
  ]
}
